vodajemokra/__init__.py
vodajemokra/auth.py
vodajemokra/client.py
vodajemokra/enums.py
vodajemokra/errors.py
vodajemokra/friend.py
vodajemokra/http.py
vodajemokra/kairos.py
vodajemokra/message.py
vodajemokra/news.py
vodajemokra/party.py
vodajemokra/playlist.py
vodajemokra/presence.py
vodajemokra/stats.py
vodajemokra/store.py
vodajemokra/typedefs.py
vodajemokra/user.py
vodajemokra/utils.py
vodajemokra/xmpp.py
vodajemokra/ext/commands/__init__.py
vodajemokra/ext/commands/_types.py
vodajemokra/ext/commands/bot.py
vodajemokra/ext/commands/cog.py
vodajemokra/ext/commands/context.py
vodajemokra/ext/commands/converter.py
vodajemokra/ext/commands/cooldown.py
vodajemokra/ext/commands/core.py
vodajemokra/ext/commands/errors.py
vodajemokra/ext/commands/typedefs.py
vodajemokra/ext/commands/view.py
vodajemokrafn-0.0.8.dist-info/LICENSE
vodajemokrafn-0.0.8.dist-info/METADATA
vodajemokrafn-0.0.8.dist-info/WHEEL
vodajemokrafn-0.0.8.dist-info/top_level.txt
vodajemokrafn-0.0.8.dist-info/RECORD
